{"date": "2015-08-07 00:00:00", "type": "regular", "spotify_uri": null, "title": "Group Therapy 142 with Above & Beyond and Yotto", "sets": [{"tracklist": [{"label": "(White)", "type": "regular", "artist": "Arty", "trackname": "‘The Wonder’ [Mat Zo Remix]"}, {"label": "(Ride)", "type": "regular", "artist": "BRKLYN x Kevin Wild feat. Lenachka", "trackname": "‘Guide Me Home’ [Fatum Remix]"}, {"label": "(Frost)", "type": "regular", "artist": "Zack Shaar", "trackname": "‘Along The Way’"}, {"label": "(Sony / Anjunabeats)", "type": "record_of_the_week", "artist": "Faithless", "trackname": "‘Salva Mea 2.0’ [Above & Beyond Remix]"}, {"label": "(Freegrant)", "type": "regular", "artist": "Thomas Mengel", "trackname": "‘Nicoya’"}, {"label": "(Trice)", "type": "regular", "artist": "Tim Mason", "trackname": "‘Output’"}, {"label": "(White)", "type": "regular", "artist": "Asmond", "trackname": "‘Orion’"}, {"label": "(Anjunabeats)", "type": "regular", "artist": "Jody Wisternoff feat. Sian Evans", "trackname": "‘The Bridge’ [Chicane Remix]"}, {"label": "(Freegrant)", "type": "regular", "artist": "Andrea Bertolini & Yuji Ono", "trackname": "‘Universe’"}, {"label": "(Wake Your Mind)", "type": "regular", "artist": "Cosmic Gate & Jennifer Cooke", "trackname": "‘This Will Be Your Happyness’ [High 5 Remix]"}, {"label": "(Enhanced Progressive)", "type": "regular", "artist": "Cannavo & Nesse", "trackname": "‘Apollo’"}, {"label": "(Silk)", "type": "regular", "artist": "Piramex", "trackname": "‘Aravia’"}, {"label": "(Pryda)", "type": "regular", "artist": "Pryda", "trackname": "‘Neuron’"}, {"label": "(Pryda)", "type": "push_the_button", "artist": "Eric Prydz", "trackname": "‘Opus’"}, {"label": "(Anjunadeep)", "type": "regular", "artist": "Solomon Grey", "trackname": "‘Twilight’ [John Monkman Remix]"}, {"label": "(NYX Music)", "type": "regular", "artist": "Eli & Fur", "trackname": "‘Your Eyes’"}, {"label": "(Suara)", "type": "regular", "artist": "Dosem", "trackname": "‘Runner Park’ [Jeremy Olander Remix]"}, {"label": "(FFRR)", "type": "regular", "artist": "Kidnap Kid", "trackname": "‘Fall’ [Oxia Remix]"}, {"label": "(Anjunabeats)", "type": "flashback", "artist": "Above & Beyond", "trackname": "‘World On Fire’"}], "artist": {"name": "Above & Beyond"}}, {"tracklist": [{"label": "(Anjunadeep)", "type": "regular", "artist": "Yotto", "trackname": "‘Slowly’ [Intro Edit]"}, {"label": "(Saved)", "type": "regular", "artist": "Hot Since 82", "trackname": "‘Play The Room’ [Matthias Meyer’s Morgenstaub Remix]"}, {"label": "(Anjunadeep)", "type": "regular", "artist": "Yotto", "trackname": "‘Mulholland 99’"}, {"label": "(Pampa Records)", "type": "regular", "artist": "Dj Koze", "trackname": "‘XTC’"}, {"label": "(White)", "type": "regular", "artist": "Moby", "trackname": "‘Why Does My Heart Feel So Bad’ [Yotto Rework]"}, {"label": "(Anjunadeep)", "type": "regular", "artist": "Yotto feat. CAPS", "trackname": "‘Wondering’"}, {"label": "(Anjunabeats)", "type": "regular", "artist": "Above & Beyond feat. Gemma Hayes", "trackname": "‘Counting Down The Days’ [Yotto Remix]"}], "type": "guestmix", "artist": {"image": "http://cms.api.aboveandbeyond.nu/", "name": "Yotto"}}], "playLink": "https://soundcloud.com/aboveandbeyond/abgt142", "youtube_link": null}