{"date": "2014-01-17 00:00:00", "type": "regular", "spotify_uri": null, "title": "Group Therapy 062 with Above & Beyond and Guy Mantzur", "sets": [{"tracklist": [{"label": "(Anjunabeats)", "type": "regular", "artist": "Andrew Bayer", "trackname": "\"Once Lydian\""}, {"label": "(Enhanced)", "type": "regular", "artist": "Soundprank", "trackname": "\"Squared\""}, {"label": "(Big Beat)", "type": "regular", "artist": "Icona Pop", "trackname": "\"Just Another Night\" [Marcus Schossow Remix]"}, {"label": "(Anjunabeats)", "type": "record_of_the_week", "artist": "Norin & Rad", "trackname": "\"Thundercat\""}, {"label": "(Enhanced)", "type": "regular", "artist": "Daniel Garrick", "trackname": "\"Upgrade\""}, {"label": "(White)", "type": "regular", "artist": "Snow Patrol", "trackname": "\"Open Your Eyes\" [Steve Brian & Oudai Abdulhadi Bootleg]"}, {"label": "(Axtone)", "type": "regular", "artist": "Deniz Koyu", "trackname": "\"Ruby\""}, {"label": "(Your Shape)\" (Flashover)", "type": "regular", "artist": "Art Shumiloff & Jenia", "trackname": "\"Roxxane"}, {"label": "(Ultra)", "type": "regular", "artist": "Black Boots", "trackname": "\"Sex Cult\" [Matt Lange Remix]"}, {"label": "(Monster)", "type": "regular", "artist": "Jason Ross", "trackname": "\"Burma\""}, {"label": "(White)", "type": "regular", "artist": "Arty vs Above & Beyond and Zoe Johnston", "trackname": "\"You Got To Believe\" [A&B Mash Up]"}, {"label": "(White)", "type": "regular", "artist": "Betoko vs. Gemma Hayes", "trackname": "\"Wicked Game\""}, {"label": "(Anjunabeats)", "type": "push_the_button", "artist": "Above & Beyond", "trackname": "\"Sun & Moon\" [Acoustic]"}, {"label": "(Virgin)", "type": "regular", "artist": "Bastille", "trackname": "\"Pompeii\" [Audien Remix]"}, {"label": "(Sudbeat)", "type": "regular", "artist": "Martin Roth", "trackname": "\"Epic Waves\""}, {"label": "(White)", "type": "regular", "artist": "London Grammar", "trackname": "\"Strong\" [Judah Remix]"}, {"label": "(Freegrant)", "type": "regular", "artist": "Max Freegrant & Yuji Ono", "trackname": "\"Tokyo Drift\""}, {"label": "(Anjunadeep)", "type": "flashback", "artist": "Michael Cassette", "trackname": "\"Shadows Movement\""}], "artist": {"name": "Above & Beyond"}}, {"tracklist": [{"label": "(Lost & Found)", "type": "regular", "artist": "Stas Drive", "trackname": "\"Apotheosis\""}, {"label": "(White)", "type": "regular", "artist": "Timo Maas feat. Katie Cruel", "trackname": "\"Articulation\" [Simon Vuarambon Space Mix]"}, {"label": "(Lost & Found)", "type": "regular", "artist": "Overture", "trackname": "\"Twice As Nice\" [Guy J Remix]"}, {"label": "(White)", "type": "regular", "artist": "Dhillon", "trackname": "\"The Heist\""}, {"label": "(White", "type": "regular", "artist": "Guy Gerbar", "trackname": "\"Stoppage Time\" [Guy Mantzur & Khen Bootleg]"}], "type": "guestmix", "artist": {"image": "http://cms.api.aboveandbeyond.nu/sites/default/files/guymantzurabgt_0.jpg", "name": "Guy Mantzur"}}], "playLink": "https://soundcloud.com/aboveandbeyond/abgt062", "youtube_link": "http://youtube.com/watch?v=810qmIRp2Y4"}